lib_mx_colab/__init__.py
lib_mx_colab/sistema.py
lib_mx_colab-0.2.6.dist-info/LICENSE
lib_mx_colab-0.2.6.dist-info/METADATA
lib_mx_colab-0.2.6.dist-info/WHEEL
lib_mx_colab-0.2.6.dist-info/top_level.txt
lib_mx_colab-0.2.6.dist-info/RECORD
