Metadata-Version: 2.1
Name: lib_mx_colab
Version: 0.2.6
Summary: IA Sistema de Interes
Home-page: https://www.youtube.com/@IA.Sistema.de.Interes
Author: IA Sistema de Interes
Author-email: system.ai.of.interest@gmail.com
Classifier: Programming Language :: Python :: 3
Classifier: License :: OSI Approved :: MIT License
Classifier: Operating System :: OS Independent
Requires-Python: >=3.6
License-File: LICENSE
Requires-Dist: requests
Requires-Dist: IPython
